{
    "id": "1fef633c-d957-44d3-b6a6-9cb32b98ce2b",
    "createdAt": "2023-08-22T18:42:31.605722",
    "name": "One pot pasta puttanesca",
    "desc": "Prova detta recept på one pot pasta puttanesca där pastan kokas tillsammans med såsen som består av en härlig kombination av oliver, sardeller och tomat. Enkelheten gör denna rätt till det perfekta valet för en god vardagsmiddag.",
    "costPerServing": 43.51,
    "servings": 4,
    "cookingTime": 45,
    "originalRecipe": "https://www.ica.se/recept/one-pot-pasta-puttanesca-729965/",
    "ingredients": [],
    "image": "https://assets.icanet.se/e_sharpen:80,q_auto,dpr_1.25,w_718,h_718,c_lfill/imagevaultfiles/id_250296/cf_259/one_pot_pasta_puttanesca.jpg",
    "steps": [
        "Skala och hacka vitlöken. Hacka sardeller och oliver. Fräs vitlöken i oljan tills den är gyllene. Tillsätt sardeller, tomatpuré och oliver och fräs ytterligare några minuter.",
        "Tillsätt vatten och pasta. Låt koka ca 8 minuter eller tills pastan är mjuk. Smaka av med salt och peppar."
    ],
    "ingredientGroups": [
        {
            "ingredients": [
                {
                    "amount": 4,
                    "measurement": "PCS",
                    "name": "vitlöksklyftor"
                },
                {
                    "amount": 6,
                    "measurement": "PCS",
                    "name": "sardellfilé"
                },
                {
                    "amount": 2,
                    "measurement": "DL",
                    "name": "svarta oliver"
                },
                {
                    "amount": 2,
                    "measurement": "TBSP",
                    "name": "olivolja"
                },
                {
                    "amount": 1,
                    "measurement": "DL",
                    "name": "tomatpuré"
                },
                {
                    "amount": 12,
                    "measurement": "DL",
                    "name": "vatten"
                },
                {
                    "amount": 400,
                    "measurement": "G",
                    "name": "makaroner"
                },
                {
                    "amount": 0,
                    "measurement": "NONE",
                    "name": "salt"
                },
                {
                    "amount": 0,
                    "measurement": "NONE",
                    "name": "svartpeppar"
                }
            ]
        }
    ]
}